oxauth/__init__.py
oxauth/strategy_2.py
oxauth-0.0.2.dist-info/LICENSE.txt
oxauth-0.0.2.dist-info/METADATA
oxauth-0.0.2.dist-info/WHEEL
oxauth-0.0.2.dist-info/top_level.txt
oxauth-0.0.2.dist-info/RECORD
