Metadata-Version: 2.1
Name: oxauth
Version: 0.0.2
Summary: OpenStax authentication strategies
Home-page: https://github.com/openstax/auth-python
Author: JP Slavinsky
Author-email: jps@rice.edu
License: UNKNOWN
Platform: UNKNOWN
Classifier: Programming Language :: Python :: 3
Classifier: License :: OSI Approved :: MIT License
Classifier: Operating System :: OS Independent
Requires-Python: >=3.6
Requires-Dist: PyJWT
Requires-Dist: PyJWE
